easy_es/.DS_Store
easy_es/__init__.py
easy_es/base.py
easy_es/data_loader.py
easy_es/estimation_models.py
easy_es/event_study_model.py
easy_es/utils.py
easy_es-0.1.8.dist-info/WHEEL
easy_es-0.1.8.dist-info/entry_points.txt
easy_es-0.1.8.dist-info/METADATA
easy_es-0.1.8.dist-info/RECORD
