Metadata-Version: 2.3
Name: easy-es
Version: 0.1.8
Summary: A package to conduct financial event study with few lines of code.
Author: Vladislav Pyzhov
Author-email: Vladislav Pyzhov <vladpyzhov@gmail.com>
Requires-Dist: nbformat>=5.10.4
Requires-Dist: numpy>=1.26,<3
Requires-Dist: pandas>=2.0,<2.3
Requires-Dist: plotly>=6,<7
Requires-Dist: pytest>=8.4.2
Requires-Dist: python-dateutil>=2.9.0.post0
Requires-Dist: scikit-learn>=1.6
Requires-Dist: scipy>=1.11,<2
Requires-Dist: statsmodels>=0.14,<0.15
Requires-Dist: tqdm>=4.66
Requires-Dist: typing-extensions>=4.8
Requires-Dist: yfinance>=0.2.36
Requires-Dist: ipykernel>=6,<7 ; extra == 'notebooks'
Requires-Dist: nbformat>=5,<6 ; extra == 'notebooks'
Requires-Python: >=3.12
Provides-Extra: notebooks
